{
  "lexicon": 1,
  "id": "fund.at.contribute",
  "description": "Declares contribution and funding entry points published by a steward DID. Canonical schema for at.fund",
  "defs": {
    "main": {
      "type": "record",
      "description": "Canonical contribution entry points published by a steward DID. Optionally restricted to specific domains via restrictToDomains.",
      "key": "tid",
      "record": {
        "type": "object",
        "properties": {
          "restrictToDomains": {
            "type": "array",
            "description": "Optional allowlist of domain/hostnames for which these contribution links should be considered applicable (e.g. example.com, pds.example.com). When omitted or empty, the record is open.",
            "items": { "type": "string" }
          },
          "links": {
            "type": "array",
            "items": { "type": "ref", "ref": "#link" }
          },
          "effectiveDate": {
            "type": "string",
            "format": "datetime"
          }
        }
      }
    },
    "link": {
      "type": "object",
      "required": ["label", "url"],
      "properties": {
        "label": { "type": "string" },
        "url": { "type": "string", "format": "uri" }
      }
    }
  }
}
